spydtest/__init__.py
spydtest/api.py
spydtest/cli.py
spydtest/cloudflare.py
spydtest-0.1.0.dist-info/LICENSE
spydtest-0.1.0.dist-info/METADATA
spydtest-0.1.0.dist-info/WHEEL
spydtest-0.1.0.dist-info/entry_points.txt
spydtest-0.1.0.dist-info/top_level.txt
spydtest-0.1.0.dist-info/RECORD
