Metadata-Version: 2.2
Name: spydtest
Version: 0.1.0
Summary: Test internet speed
Author: oskvr37
License: MIT License
Project-URL: homepage, https://github.com/oskvr37/spydtest
Classifier: Environment :: Console
Classifier: Programming Language :: Python :: 3
Classifier: Operating System :: OS Independent
Classifier: License :: OSI Approved :: MIT License
Requires-Python: >=3.11
License-File: LICENSE
Requires-Dist: urllib3>=2.3.0
Requires-Dist: pydantic>=2.10.0
Requires-Dist: rich>=13.6.0
